clade/__init__.py
clade/__main__.py
clade/abstract.py
clade/cmds.py
clade/debugger.py
clade/envs.py
clade/intercept.py
clade/libinterceptor.py
clade/server.py
clade/utils.py
clade/wrapper.py
clade/extensions/__init__.py
clade/extensions/abstract.py
clade/extensions/alternatives.py
clade/extensions/ar.py
clade/extensions/assembler.py
clade/extensions/callgraph.py
clade/extensions/calls_by_ptr.py
clade/extensions/cc.py
clade/extensions/cdb.py
clade/extensions/cl.py
clade/extensions/cmd_graph.py
clade/extensions/common.py
clade/extensions/common_info.py
clade/extensions/compiler.py
clade/extensions/cross_ref.py
clade/extensions/cxx.py
clade/extensions/functions.py
clade/extensions/info.py
clade/extensions/install.py
clade/extensions/ld.py
clade/extensions/link.py
clade/extensions/linker.py
clade/extensions/ln.py
clade/extensions/macros.py
clade/extensions/mv.py
clade/extensions/objcopy.py
clade/extensions/opts.py
clade/extensions/path.py
clade/extensions/pid_graph.py
clade/extensions/src_graph.py
clade/extensions/storage.py
clade/extensions/typedefs.py
clade/extensions/used_in.py
clade/extensions/utils.py
clade/extensions/variables.py
clade/extensions/win_copy.py
clade/extensions/info/info.aspect
clade/extensions/info/linux_kernel.aspect
clade/extensions/presets/presets.json
clade/intercept/CMakeLists.txt
clade/intercept/debugger.exe
clade/intercept/unix/CMakeLists.txt
clade/intercept/unix/client.c
clade/intercept/unix/client.h
clade/intercept/unix/data.c
clade/intercept/unix/data.h
clade/intercept/unix/env.c
clade/intercept/unix/env.h
clade/intercept/unix/interceptor.c
clade/intercept/unix/lock.c
clade/intercept/unix/lock.h
clade/intercept/unix/which.c
clade/intercept/unix/which.h
clade/intercept/unix/wrapper.c
clade/intercept/windows/CMakeLists.txt
clade/intercept/windows/client.cpp
clade/intercept/windows/client.h
clade/intercept/windows/debugger.cpp
clade/scripts/__init__.py
clade/scripts/check.py
clade/scripts/compilation_database.py
clade/scripts/diff.py
clade-4.1.dist-info/LICENSE
clade-4.1.dist-info/METADATA
clade-4.1.dist-info/WHEEL
clade-4.1.dist-info/entry_points.txt
clade-4.1.dist-info/top_level.txt
clade-4.1.dist-info/RECORD
